cooldata/__init__.py
cooldata/dgl_flow_field_dataset.py
cooldata/metadata.py
cooldata/pyg_flow_field_dataset.py
cooldata/pyvista_flow_field_dataset.py
cooldata/voxel_flow_field_dataset.py
cooldata-1.0.2.dist-info/METADATA
cooldata-1.0.2.dist-info/WHEEL
cooldata-1.0.2.dist-info/RECORD
