Metadata-Version: 2.4
Name: cooldata
Version: 1.0.2
Summary: Cooldata - A Large-Scale Electronics Cooling 3D Flow Field Dataset
Project-URL: Homepage, https://cooldata.readthedocs.io/
Project-URL: Repository, https://github.com/peteole/flow_field_dataset
Author: Eya Chouaib, Firas Drass, Jana Huhne, Ole Petersen, Beatrice Picco, Daniel Schenk
Requires-Python: >=3.11
Requires-Dist: huggingface-hub>=0.27.1
Requires-Dist: ipykernel>=6.29.5
Requires-Dist: lightning>=2.5.1.post0
Requires-Dist: pandas>=2.2.3
Requires-Dist: pyarrow>=19.0.1
Requires-Dist: pyransame>=0.4.0
Requires-Dist: pyvista[all]>=0.44.2
Requires-Dist: tensordict>=0.5.0
Requires-Dist: torch-geometric>=2.6.1
Requires-Dist: torch>=2.3.0
Requires-Dist: torchvision>=0.19.0
Requires-Dist: tqdm>=4.67.1
